src/__init__.py
src/__main__.py
src/config.py
src/handlers/__init__.py
src/handlers/args.py
src/handlers/attack.py
src/handlers/client.py
src/handlers/color.py
src/handlers/crack.py
src/handlers/handshake.py
src/handlers/input.py
src/handlers/process.py
src/handlers/result.py
src/handlers/scanner.py
src/handlers/target.py
src/handlers/timer.py
src/plugins/__init__.py
src/plugins/aircrack.py
src/plugins/aireplay.py
src/plugins/airmon.py
src/plugins/airodump.py
src/plugins/bully.py
src/plugins/cowpatty.py
src/plugins/dependency.py
src/plugins/hashcat.py
src/plugins/ifconfig.py
src/plugins/iwconfig.py
src/plugins/john.py
src/plugins/macchanger.py
src/plugins/pyrit.py
src/plugins/reaver.py
src/plugins/tshark.py
src/plugins/wash.py
src/tools/__init__.py
src/tools/all.py
src/tools/pmkid.py
src/tools/wep.py
src/tools/wpa.py
src/tools/wps.py
wifihunter-1.0.0.data/data/share/dict/wordlist-top4800-probable.txt
wifihunter-1.0.0.data/scripts/wifihunter.py
wifihunter-1.0.0.dist-info/LICENSE
wifihunter-1.0.0.dist-info/METADATA
wifihunter-1.0.0.dist-info/WHEEL
wifihunter-1.0.0.dist-info/entry_points.txt
wifihunter-1.0.0.dist-info/top_level.txt
wifihunter-1.0.0.dist-info/RECORD
