Metadata-Version: 2.1
Name: wifihunter
Version: 1.0.0
Summary: WiFi Penetration Toolkit
Home-page: https://github.com/MA24th/WiFiHunter
Author: Mustafa Asaad
Author-email: ma24th@yahoo.com
License: GNU GPLv2
Keywords: wifi penetration toolkit
Platform: UNKNOWN
Classifier: Programming Language :: Python :: 3
Classifier: Environment :: Console
Classifier: License :: OSI Approved :: GNU General Public License v2 (GPLv2)
